[
    {
        "TITLE": "우리銀, 금융사고 예방 위한 이상징후 검사시스템 가동",
        "CATEGORY_NAMES": "경제>금융_재테크<font color=Gray> | </font>IT_과학>과학<font color=Gray> | </font>IT_과학>모바일",
        "URL": "https://www.bigkinds.or.kr/v2/news/newsDetailView.do?newsId=02100311.20250224142310001",
        "DATE": "20250224",
        "PROVIDER": "서울경제",
        "CONTENT": "우리은행이 선제적 금융사고 예방과 내부통제 혁신 방안의 일환으로 금융사고 패턴을 이용해 문제 거래를 탐지하는 이상징후검사시스템(FDS)를 24일부터 가동한다고 밝혔다. <br/> <br/><br/> 이는 임종룡 우리금융그룹 회장이 지난해 10월 국정감사에서 올해부터 이상징후 탐지 체계를 구축해 시행하겠다고 발표한 데 따른 조치다. 이번 시스템 구축으로 은행권에서는 처음으로 .."
    },
    {
        "TITLE": "송기섭 진천군수 기업체 현장 방문",
        "CATEGORY_NAMES": "경제>자동차<font color=Gray> | </font>지역>경북<font color=Gray> | </font>지역>강원",
        "URL": "https://www.bigkinds.or.kr/v2/news/newsDetailView.do?newsId=01400551.20250224142259001",
        "DATE": "20250224",
        "PROVIDER": "충북일보",
        "CONTENT": "［충북일보］ 송기섭 진천군수는 24일 지역 강소기업 ㈜엠알인프라오토를 찾아 원활한 기업경영 지원방안에 대해 의견을 수렴했다. <br/><br/>송 군수는 새해 첫 기업방문 일정으로 ㈜엠알인프라오토 공장 1·2동 생산설비를 직접 둘러보고 기업의 애로사항을 경청했다. <br/><br/>이어 근로자들과 함께 식사하며 직원들을 격려하는 시간도 가졌다. <br/><br/>송 군수는 \"국가적 혼란상태가 지.."
    },
    {
        "TITLE": "포르쉐 타이칸, 한국자동차기자협회 '2025 올해의 퍼포먼스' 수상",
        "CATEGORY_NAMES": "경제>자동차<font color=Gray> | </font>IT_과학>과학<font color=Gray> | </font>경제>반도체",
        "URL": "https://www.bigkinds.or.kr/v2/news/newsDetailView.do?newsId=07100501.20250224142253002",
        "DATE": "20250224",
        "PROVIDER": "전자신문",
        "CONTENT": "포르쉐코리아는 한국자동차기자협회(KAJA)가 주관한 2025 대한민국 올해의 차(K-COTY) 시상식에서 포르쉐 순수 전기 스포츠카 타이칸이 '2025 올해의 퍼포먼스' 부문을 수상했다고 밝혔다.<br/><br/>광범위한 업그레이드를 거친 타이칸 부분 변경 모델은 이번 심사에서 강력한 주행 성능, 긴 주행 거리, 빠른 충전 속도 등으로 전기 스포츠카의 새로운 기준을 .."
    },
    {
        "TITLE": "[ET포토] 하츠투하츠, '8인의 매력'",
        "CATEGORY_NAMES": "문화>방송_연예<font color=Gray> | </font>문화>전시_공연<font color=Gray> | </font>문화>출판",
        "URL": "https://www.bigkinds.or.kr/v2/news/newsDetailView.do?newsId=07100501.20250224142253001",
        "DATE": "20250224",
        "PROVIDER": "전자신문",
        "CONTENT": "SM 신인 그룹 하츠투하츠(Hearts2Hearts/ 지우, 카르멘, 유하, 스텔라, 주은, 에이나, 이안, 예온)가 24일 서울 광진구 예스24라이브홀에서 진행된 데뷔 싱글 ‘The Chase’ 데뷔 쇼케이스에 일정에 참석했다.<br/>타이틀곡 ‘The Chase’(더 체이스)는 몽환적인 사운드 소스들과 보컬 멜로디가 어우러져 신비롭고 묘한 분위기를 자아내는.."
    },
    {
        "TITLE": "서울 대중교통 통합 브랜드 탄생…‘GO SEOUL(고 서울)’",
        "CATEGORY_NAMES": "경제>자동차<font color=Gray> | </font>경제>서비스_쇼핑<font color=Gray> | </font>경제>유통",
        "URL": "https://www.bigkinds.or.kr/v2/news/newsDetailView.do?newsId=01100801.20250224142242001",
        "DATE": "20250224",
        "PROVIDER": "조선일보",
        "CONTENT": "서울시가 24일 버스·지하철 등 서울 대중교통을 상징하는 통합 브랜드 ‘GO SEOUL(고 서울)’을 발표했다. 이처럼 대중교통을 상징하는 브랜드를 만든 것은 전국 지자체 중 서울시가 처음이다. <br/> <br/>서울시가 ‘고 서울’을 만든 것은 서울 시민과 외국인 관광객들이 대중교통을 보다 편리하게 이용할 수 있도록 하기 위해서다. <br/> <br/>오세훈 서울시장은 이날 열.."
    },
    {
        "TITLE": "하츠투하트 지우, 자신만만",
        "CATEGORY_NAMES": "문화>전시_공연",
        "URL": "https://www.bigkinds.or.kr/v2/news/newsDetailView.do?newsId=04100158.20250224142238002",
        "DATE": "20250224",
        "PROVIDER": "데일리안",
        "CONTENT": "하츠투하츠((Hearts2Hearts) 첫 싱글 발매 기념 미디어 쇼케이스가 24일 오후 서울 광진구 예스24 라이브홀에서 열렸다. <br/><br/><br/>이날 하츠투하츠 지우가 포즈를 취하고 있다."
    },
    {
        "TITLE": "하츠투하츠 '오늘 데뷔 합니다'",
        "CATEGORY_NAMES": "문화>전시_공연<font color=Gray> | </font>문화>방송_연예",
        "URL": "https://www.bigkinds.or.kr/v2/news/newsDetailView.do?newsId=04100158.20250224142238001",
        "DATE": "20250224",
        "PROVIDER": "데일리안",
        "CONTENT": "하츠투하츠((Hearts2Hearts) 첫 싱글 발매 기념 미디어 쇼케이스가 24일 오후 서울 광진구 예스24 라이브홀에서 열렸다. <br/><br/><br/>이날 하츠투하츠가 포즈를 취하고 있다."
    },
    {
        "TITLE": "“얼죽신이 맞았네”…강남구 평당 880만원 오를 때 서초구 1300만원 올랐다[부동산360]",
        "CATEGORY_NAMES": "경제>부동산<font color=Gray> | </font>경제>유통<font color=Gray> | </font>경제>금융_재테크",
        "URL": "https://www.bigkinds.or.kr/v2/news/newsDetailView.do?newsId=02100701.20250224142238001",
        "DATE": "20250224",
        "PROVIDER": "헤럴드경제",
        "CONTENT": "KB부동산 2월 월간시계열 발표 <br/><br/> 서울 서초구 반포동 ‘래미안원베일리’ 아파트 전경. 신혜원 기자<br/> <br/><br/>[헤럴드경제=홍승희 기자] 지난 1년간 서초구의 아파트의 평(3.3㎡)당 평균 매매가격이 강남구보다 50% 이상 빠른 속도로 급등한 것으로 나타났다. 서초구 반포동의 일부 신축 아파트는 서초구뿐 아니라 서울의 전체 평균 매매가격도 끌어올리고 있다..."
    },
    {
        "TITLE": "삼성SDI, 2년 연속 '인터배터리 어워즈' 수상",
        "CATEGORY_NAMES": "IT_과학>과학<font color=Gray> | </font>경제>유통<font color=Gray> | </font>IT_과학>모바일",
        "URL": "https://www.bigkinds.or.kr/v2/news/newsDetailView.do?newsId=02100601.20250224142238001",
        "DATE": "20250224",
        "PROVIDER": "한국경제",
        "CONTENT": "삼성SDI가 국내 최대 규모의 배터리 전시회에서 2년 연속 기술력을 인정받았다. <br/> <br/>삼성SDI는 '50A급 초고출력 원통형 배터리'와 'LFP+ 플랫폼 소재·극판 기술'이 '인터배터리 어워즈 2025' 수상작으로 선정됐다고 24일 밝혔다. <br/> <br/>한국배터리산업협회는 다음달 5일부터 사흘간 삼성동 코엑스에서 '인터배터리 2025'를 개최한다. 이에 앞서 .."
    },
    {
        "TITLE": "“세금을 알아야 월급도 지킵니다”… 세금 공부 먼저 하세요 [책의향기 온라인]",
        "CATEGORY_NAMES": "문화>출판<font color=Gray> | </font>사회>교육_시험",
        "URL": "https://www.bigkinds.or.kr/v2/news/newsDetailView.do?newsId=01100401.20250224142237001",
        "DATE": "20250224",
        "PROVIDER": "동아일보",
        "CONTENT": "◇ 세상 친절한 세금 수업/김현주 지음/288쪽·1만9000원·미래의창 <br/> <br/>‘매년 하는 연말정산이지만 솔직히 매번 아리송하다. 회사에서 해주는 대로만 받아 왔는데, 어느 날 궁금해졌다. 연말정산 환급액, 왜 누구는 더 받고 누구는 덜 받는 걸까.’ <br/> <br/>‘큰돈이 있을 리 없는 청년들이 집을 구매할 때 어쩔 수 없이 부모님의 도움을 받게 되는 경우가 있.."
    },
    {
        "TITLE": "양재생 부산상의회장, 회원사 방문·CEO 간담회 개최",
        "CATEGORY_NAMES": "지역>부산<font color=Gray> | </font>지역>대전<font color=Gray> | </font>지역>경남",
        "URL": "https://www.bigkinds.or.kr/v2/news/newsDetailView.do?newsId=02100801.20250224142237001",
        "DATE": "20250224",
        "PROVIDER": "아시아경제",
        "CONTENT": "부산상공회의소 양재생 회장은 24일 피팅·밸브 제조 전문기업 비엠티를 방문해 제조 현장을 둘러보고 당면 애로사항을 청취하는 현장간담회를 가졌다. <br/> <br/>이번 방문은 글로벌 불확실성의 확대와 지속되는 경기침체 속에서 지역 기업들이 직면한 애로들을 현장에서 직접 점검하기 위해 이뤄졌다.양재생 회장은 실효성 있는 지원 대책을 마련하기 위해 지난해 9월부터 직접.."
    },
    {
        "TITLE": "이데일리 송승현 기자, 대한변협 선정 우수언론인상 수상",
        "CATEGORY_NAMES": "경제>경제일반",
        "URL": "https://www.bigkinds.or.kr/v2/news/newsDetailView.do?newsId=04101008.20250224142227001",
        "DATE": "20250224",
        "PROVIDER": "이데일리",
        "CONTENT": "[이데일리 최오현 기자] 이데일리 송승현 기자가 대한변호사협회 우수언론인상을 수상했다.<br/><br/>변협은 24일 오전 서울 중구 소공동 롯데호텔에서 개최한 2025년도 정기총회에서 송승현 이데일리 기자(왼쪽에서 5번째) 등 언론인 6명을 우수언론인상 수상자로 선정해 시상했다.(사진=대한변호사협회)대한변협은 24일 오전 서울 중구 소공동 롯데호텔에서 개최한 202.."
    },
    {
        "TITLE": "[포토] 하츠투하츠 에이나 '매력적인 볼하트'",
        "CATEGORY_NAMES": "문화>전시_공연<font color=Gray> | </font>문화>방송_연예<font color=Gray> | </font>문화>출판",
        "URL": "https://www.bigkinds.or.kr/v2/news/newsDetailView.do?newsId=01100701.20250224142209001",
        "DATE": "20250224",
        "PROVIDER": "세계일보",
        "CONTENT": "SM엔터테인먼트의 신인 걸그룹 하츠투하츠(Hearts2Hearts) 에이나가 24일 오후 서울 광진구 예스24 라이브홀에서 열린 첫 싱글 ‘더 체이스’(The Chase)의 쇼케이스 무대에 참석해 포즈를 취하고 있다. <br/> <br/> 타이틀곡 ‘더 체이스’는 몽환적인 사운드 소스들과 보컬 멜로디가 어우러져 신비롭고 묘한 분위기를 자아내는 곡으로, 강렬하고 독특한.."
    },
    {
        "TITLE": "충남북부상의 입찰정보시스템 사업 추진",
        "CATEGORY_NAMES": "경제>부동산<font color=Gray> | </font>IT_과학>보안<font color=Gray> | </font>IT_과학>모바일",
        "URL": "https://www.bigkinds.or.kr/v2/news/newsDetailView.do?newsId=01400601.20250224142208001",
        "DATE": "20250224",
        "PROVIDER": "충청일보",
        "CONTENT": "-작년 총 1092건, 1675억원 낙찰 <br/><br/>충남북부상공회의소(회장 문상인)는 24일 지난해 충남형 입찰정보시스템 사업을 추진해 총 1092건, 1675억원 낙찰 성과를 달성했다고 밝혔다. <br/><br/>충남북부상의에 따르면 입찰정보시스템 사업은 전국 공공기관 및 민간 발주처에서 제공하는 입찰 및 낙찰 정보를 실시간으로 맞춤 제공할 뿐 아니라 가입한 기업체에게는 .."
    },
    {
        "TITLE": "인천 동구, 저소득층 아동에 예체능 수강료 지원",
        "CATEGORY_NAMES": "지역>대전<font color=Gray> | </font>지역>경기<font color=Gray> | </font>지역>전북",
        "URL": "https://www.bigkinds.or.kr/v2/news/newsDetailView.do?newsId=01400501.20250224142208001",
        "DATE": "20250224",
        "PROVIDER": "중부일보",
        "CONTENT": "인천 동구가 형편상 학원 수강에 어려움을 겪는 가정에 예체능 학원비를 지원하는 사업을 지난해에 이어 올해도 추진한다고 24일 밝혔다. <br/><br/>저소득가정 아동 예체능 수강료 지원사업은 동구에 거주하는 기초생활보장 수급자(기초생계ㆍ의료ㆍ주거ㆍ교육급여) 및 저소득 한부모가정 초등학생에게 국ㆍ영ㆍ수를 제외한 구내 예체능 학원 이용시 매월 최대 10만 원의 수강료를.."
    },
    {
        "TITLE": "비명계 잠룡들, 잇달아 “이낙연, 연대와 통합 대상”",
        "CATEGORY_NAMES": "정치>국회_정당<font color=Gray> | </font>정치>선거<font color=Gray> | </font>정치>청와대",
        "URL": "https://www.bigkinds.or.kr/v2/news/newsDetailView.do?newsId=01100701.20250224142208001",
        "DATE": "20250224",
        "PROVIDER": "세계일보",
        "CONTENT": "더불어민주당 비명(비이재명)계 대선 잠룡들이 24일 이재명 대표와 각을 세우고 있는 이낙연 전 국무총리를 ‘연대와 통합’의 대상으로 평가하며 탄핵 정국 속 관련 논의가 진행돼야 한다는 뜻을 밝혔다. 친명(친이재명) 일변도의 민주당을 탈당해 새미래민주당(새민주당)으로 옮긴 이 전 총리는 ‘윤석열·이재명 동반청산’을 주장하고 있어 ‘민주·새민주 연대’가 현.."
    },
    {
        "TITLE": "[르포] \"오늘도 빈손\"…건설경기 부진에 일용직 일감이 없다",
        "CATEGORY_NAMES": "경제>취업_창업<font color=Gray> | </font>사회>노동_복지<font color=Gray> | </font>경제>금융_재테크",
        "URL": "https://www.bigkinds.or.kr/v2/news/newsDetailView.do?newsId=01100751.20250224142158001",
        "DATE": "20250224",
        "PROVIDER": "아시아투데이",
        "CONTENT": "아시아투데이 이정연 기자 = \"가장의 역할. 아빠의 역할. 아들의 역할. 각자 다 있단 말이에요. 그냥 들어가긴 미안하니까 해뜨면 전철 타고 한 바퀴 돌다가 들어갑니다.\" 24일 이른 새벽 서울 도봉구 창동역 인근의 한 인력사무소에는 건설 일감을 얻기 위해 모인 근로자 20여명이 서성이고 있었다. 이름이 불리기를 기다리다 끝내 일감을 받지 못 한 이들은.."
    },
    {
        "TITLE": "순천시 위기가구 발굴 신고자 '포상금' 5만원 지급",
        "CATEGORY_NAMES": "사회>사회일반<font color=Gray> | </font>지역>충남<font color=Gray> | </font>지역>충북",
        "URL": "https://www.bigkinds.or.kr/v2/news/newsDetailView.do?newsId=04100058.20250224142155001",
        "DATE": "20250224",
        "PROVIDER": "노컷뉴스",
        "CONTENT": "순천시청. 고영호 기자 <br/>순천시가 복지사각지대 위기가구 발굴에 대한 사회적 관심도를 높이고 신고 활성화를 위해 포상금제도를 운영한다. <br/>  <br/>신고대상은 실직, 폐업, 질병, 장애 등으로 소득이 없거나 위기 상황에 처해 도움이 필요한 순천시에 주민등록을 둔 가구이며, 읍면동행정복지센터 방문이나 전화, 복지위기 알림 앱을 통해서 신고할 수 있다. <br/>  <br/>위.."
    },
    {
        "TITLE": "'잔디 보호' 충주시, 4월 30일까지 파크골프장 5곳 휴장",
        "CATEGORY_NAMES": "지역>충북<font color=Gray> | </font>지역>강원<font color=Gray> | </font>지역>대전",
        "URL": "https://www.bigkinds.or.kr/v2/news/newsDetailView.do?newsId=04100058.20250224142154001",
        "DATE": "20250224",
        "PROVIDER": "노컷뉴스",
        "CONTENT": "충주시 제공 <br/>충북 충주시가 다음 달부터 4월 30일까지 두 달 동안 잔디 보호를 위해 파크골프장 5곳을 휴장하기로 했다고 밝혔다. <br/> <br/>충주호와 단월, 수안보, 서충주, 앙성 파크골프장이 대상이다.  <br/> <br/>휴장 기간 동안 잔디 깎기, 보식, 비료공급, 병충해 방제 등을 통해 잔디를 집중적으로 관리할 계획이다. <br/> <br/>시는 오는 5월 신니면(7천㎡, 9홀.."
    },
    {
        "TITLE": "충남세종농협, 올해 첫 “찾아가는 농기계 순회수리” 봉사",
        "CATEGORY_NAMES": "지역>충남<font color=Gray> | </font>지역>전북<font color=Gray> | </font>지역>대전",
        "URL": "https://www.bigkinds.or.kr/v2/news/newsDetailView.do?newsId=04102008.20250224142153001",
        "DATE": "20250224",
        "PROVIDER": "쿠키뉴스",
        "CONTENT": "충남세종농협 정해웅 본부장(가운데)이 24일 유구농협에서 농기계 순회수리 담당자의 이야기를 듣고 있다.  <br/>충남세종농협은 상대적으로 농기계 수리 취약지역에 거주하는 농업인들의 불편을 덜어주고자 24일 공주시 유구농협에서 올해 첫 농기계 순회수리 봉사활동을 실시했다.  <br/> <br/>이번 순회수리봉사는 본격적인 영농철을 앞두고 농가의 경영비 부담 경감을 목적으로 .."
    },
    {
        "TITLE": "“성폭력 피해자 위해 써 주세요”…故 길원옥 할머니 유족, 기부금 1000만원 전달",
        "CATEGORY_NAMES": "사회>여성<font color=Gray> | </font>사회>교육_시험",
        "URL": "https://www.bigkinds.or.kr/v2/news/newsDetailView.do?newsId=01100801.20250224142147001",
        "DATE": "20250224",
        "PROVIDER": "조선일보",
        "CONTENT": "“돌아가신 어머님이 환하게 웃으면서, 잘했다고 칭찬해 주실 것 같습니다.” <br/> <br/>일본군 위안부 피해자 고(故) 길원옥 할머니의 유족이 24일 “성폭력 피해자들을 돕는 일에 써 달라”며 인천시에 성금 1000만원을 전달했다. <br/> <br/>길 할머니의 며느리 조근순(67)씨는 이날 오전 인천시청에서 기부금을 전달한 직후 “어머님을 잘 보내드리기 위해 무엇을 할까 .."
    },
    {
        "TITLE": "혼다코리아, '제16회 혼다 CS 콘테스트' 개최",
        "CATEGORY_NAMES": "경제>자동차<font color=Gray> | </font>IT_과학>모바일<font color=Gray> | </font>IT_과학>콘텐츠",
        "URL": "https://www.bigkinds.or.kr/v2/news/newsDetailView.do?newsId=07100501.20250224142142002",
        "DATE": "20250224",
        "PROVIDER": "전자신문",
        "CONTENT": "혼다코리아는 경기도 이천에 위치한 혼다 에듀케이션 센터에서 자동차 서비스 역량 경진대회 '제16회 혼다 CS 콘테스트'를 개최했다고 24일 밝혔다.<br/><br/>혼다 CS 콘테스트는 고객 서비스 역량 강화를 위해 2005년부터 실시한 대회로, 올해에는 일반 정비·판금·도장·서비스 어드바이저·부품 등 총 5개 부문에서 우승자를 선발했다.<br/><br/>일반 정비 부문 우승자와 .."
    },
    {
        "TITLE": "KT클라우드, 엔비디아 H200 적용 고성능 AI 인프라 제공",
        "CATEGORY_NAMES": "IT_과학>인터넷_SNS<font color=Gray> | </font>IT_과학>모바일<font color=Gray> | </font>경제>자동차",
        "URL": "https://www.bigkinds.or.kr/v2/news/newsDetailView.do?newsId=07100501.20250224142142001",
        "DATE": "20250224",
        "PROVIDER": "전자신문",
        "CONTENT": "KT클라우드가 서비스형 그래픽처리장치(GPUaaS)에 엔비디아 H200을 적용하고, 고성능 인공지능(AI) 인프라를 제공한다.<br/><br/>KT클라우드는 기존 H100 중심으로 운영되던 AI 트레인 서비스에 H200을 적용한다. AI 트레인은 단기간 대용량·고사양 GPU가 요구되는 학습 영역에 특화됐다.<br/><br/>KT클라우드는 AI 트레인 뿐만 아니라 적은 양의 GPU를.."
    },
    {
        "TITLE": "헤라, 고지속 '센슈얼 틴티드 샤인 스틱' 출시",
        "CATEGORY_NAMES": "경제>서비스_쇼핑<font color=Gray> | </font>경제>유통<font color=Gray> | </font>경제>자동차",
        "URL": "https://www.bigkinds.or.kr/v2/news/newsDetailView.do?newsId=06101202.20250224142141001",
        "DATE": "20250224",
        "PROVIDER": "주간한국",
        "CONTENT": "[주간한국 손재하 기자] 아모레퍼시픽은 뷰티 브랜드 헤라가 립스틱 ‘센슈얼 틴티드 샤인 스틱’을 새롭게 출시했다고 24일 밝혔다. <br/><br/>이번 신제품은 처음 바른 발색 그대로 착색되는 샤인 제형의 립스틱이다. 맑고 선명한 색상이 12시간 유지된다. 이는 기존 샤인 립스틱의 한계로 꼽혔던 지속력 부분을 보완한 것이다. 방수 기능도 개선됐다. <br/><br/>색상은 핑크톤.."
    },
    {
        "TITLE": "정일영 의원, '바이오 특별법' 발의…“반도체·자동차 잇는 신 경제동력 만들자”",
        "CATEGORY_NAMES": "경제>경제일반<font color=Gray> | </font>정치>국회_정당<font color=Gray> | </font>IT_과학>IT_과학일반",
        "URL": "https://www.bigkinds.or.kr/v2/news/newsDetailView.do?newsId=07100501.20250224142141001",
        "DATE": "20250224",
        "PROVIDER": "전자신문",
        "CONTENT": "국회 기획재정위원회 소속 정일영 더불어민주당 의원은 24일 국가적 차원의 바이오산업 육성을 위한 '제약바이오헬스산업 진흥 및 역량 강화를 위한 특별법안(이하 바이오특별법)'을 대표발의했다.<br/><br/>바이오산업은 보건·의료, 사회, 경제, 안보 등 전략적 가치를 지닌 핵심산업이다. 바이오 기술개발과 산업 전반에 대한 지원 필요성이 제기돼 왔다. 코로나19 팬데믹.."
    },
    {
        "TITLE": "국립칠곡숲체원 지역자원 연계 숲여행 활성화를 위한 3자 간 업무협약 체결",
        "CATEGORY_NAMES": "지역>충남<font color=Gray> | </font>지역>충북<font color=Gray> | </font>지역>경기",
        "URL": "https://www.bigkinds.or.kr/v2/news/newsDetailView.do?newsId=01500501.20250224142136001",
        "DATE": "20250224",
        "PROVIDER": "대구일보",
        "CONTENT": "국립칠곡숲체원은 24일 칠곡군 농업기술센터, 칠곡군치유관광연구회와 ‘농촌 경제 및 산림복지서비스 제공 활성화’를 위한 3자 간 업무협약(MOU)을 체결했다. <br/> <br/> 국립칠곡숲체원은 24일 칠곡군 농업기술센터, 칠곡군치유관광연구회와 ‘농촌 경제 및 산림복지서비스 제공 활성화’를 위한 3자 간 업무협약(MOU)을 체결했다. <br/> <br/> 이임철 기자 im72@id.."
    },
    {
        "TITLE": "\"보안 카메라도 똑똑하게\"… 'KT 홈캠 안심' 출시",
        "CATEGORY_NAMES": "IT_과학>보안<font color=Gray> | </font>IT_과학>모바일<font color=Gray> | </font>IT_과학>콘텐츠",
        "URL": "https://www.bigkinds.or.kr/v2/news/newsDetailView.do?newsId=04100958.20250224142135002",
        "DATE": "20250224",
        "PROVIDER": "EBN",
        "CONTENT": "KT가 가정용 스마트 보안 카메라 ‘KT 홈캠 안심’을 출시한다. <br/><br/>24일 업계에 따르면 홈 폐쇄회로(CC)TV 이용자가 늘고 있는 가운데 해킹으로 인한 사생활 유출 우려가 커지고 있다. 하지만 해킹 여부를 확인하는 방법이 발광다이오드(LED) 변화나 로그인 기록 확인 등에 의존해 명확하지 않아 보안 불안이 지속되고 있다. <br/><br/>KT가 군사기밀 관리 수.."
    },
    {
        "TITLE": "삼성전자 노사, 임금·단체협약 잠정 합의…임금인상률 5.1%",
        "CATEGORY_NAMES": "사회>노동_복지",
        "URL": "https://www.bigkinds.or.kr/v2/news/newsDetailView.do?newsId=04100958.20250224142135001",
        "DATE": "20250224",
        "PROVIDER": "EBN",
        "CONTENT": "삼성전자 노사가 평균 임금인상률 5.1%, 자사주 30주 지급 등을 골자로 하는 올해 임금ㆍ단체협약을 마무리했다. <br/><br/>삼성전자와 전국삼성전자노동조합은 24일 2025년 임금ㆍ단체협약의 잠정합의안을 도출했다고 밝혔다. <br/><br/>2025년 임금교섭을 본격 시작한 지난 1월 7일 이후 약 48일만이며 작년부터 이어온 단체교섭도 이번 임금교섭과 병행해 마무리했다. .."
    },
    {
        "TITLE": "성주군, 과수화상병 사전예방 본격 돌입! 농가들 주의 당부",
        "CATEGORY_NAMES": "지역>충남<font color=Gray> | </font>지역>울산<font color=Gray> | </font>지역>경남",
        "URL": "https://www.bigkinds.or.kr/v2/news/newsDetailView.do?newsId=01500501.20250224142135001",
        "DATE": "20250224",
        "PROVIDER": "대구일보",
        "CONTENT": "성주군청 전경 성주군은 올해 식물방역법 시행령 개정에 따라 ‘과수화상병’의 발생을 사전 차단하기 위해 사과와 배 재배농가를 대상으로 농가교육에 나서는 등 초비상이 걸렸다. <br/> <br/> 과수화상병은 식물검역병으로 국내 확산 방지를 위해 주요 기주작물인 사과와 배에 대한 예방적 약제방제가 의무화 돼 있다. 이로인해 성주군은 사과와 배 재배농가 332호(161.9.."
    },
    {
        "TITLE": "하츠투하트 카르멘, 귀여움은 내 담당",
        "CATEGORY_NAMES": "문화>전시_공연",
        "URL": "https://www.bigkinds.or.kr/v2/news/newsDetailView.do?newsId=04100158.20250224142135002",
        "DATE": "20250224",
        "PROVIDER": "데일리안",
        "CONTENT": "하츠투하츠((Hearts2Hearts) 첫 싱글 발매 기념 미디어 쇼케이스가 24일 오후 서울 광진구 예스24 라이브홀에서 열렸다. <br/><br/><br/>이날 하츠투하츠 카르멘이 포즈를 취하고 있다."
    },
    {
        "TITLE": "하츠투하트 에이나, 미소 살짝",
        "CATEGORY_NAMES": "문화>종교<font color=Gray> | </font>문화>전시_공연",
        "URL": "https://www.bigkinds.or.kr/v2/news/newsDetailView.do?newsId=04100158.20250224142135001",
        "DATE": "20250224",
        "PROVIDER": "데일리안",
        "CONTENT": "하츠투하츠((Hearts2Hearts) 첫 싱글 발매 기념 미디어 쇼케이스가 24일 오후 서울 광진구 예스24 라이브홀에서 열렸다. <br/><br/><br/>이날 하츠투하츠 이안이 포즈를 취하고 있다."
    },
    {
        "TITLE": "대동, 북미 최대 농기계 전시회서 기술 뽐내",
        "CATEGORY_NAMES": "경제>자동차",
        "URL": "https://www.bigkinds.or.kr/v2/news/newsDetailView.do?newsId=01500601.20250224142135001",
        "DATE": "20250224",
        "PROVIDER": "매일신문",
        "CONTENT": "대동은 북미 최대 농기계 전시회인 '세계 농업 박람회'와 '루이빌 농기계 전시회'에 참가했다고 24일 밝혔다. <br/> <br/> 대동은 지난 11~13일 개최한 세계농업박람회와 12~15일 열린 루이빌농기계전시회에서 북미 주력 20∼60마력대의 중소형 트랙터 CS, CX, CK, DK 모델을 비롯해 올해 본격 사업 확장을 계획하고 있는 70∼140마력대 HX, R.."
    },
    {
        "TITLE": "대구 군위군 새마을회, 대구마라톤대회 참가해 군부대 유치 홍보",
        "CATEGORY_NAMES": "지역>대구<font color=Gray> | </font>지역>경남<font color=Gray> | </font>지역>충북",
        "URL": "https://www.bigkinds.or.kr/v2/news/newsDetailView.do?newsId=01500501.20250224142134001",
        "DATE": "20250224",
        "PROVIDER": "대구일보",
        "CONTENT": "대구 군위군 새마을회는 지난 23일 대구마라톤대회에 참가해 대구 새마을회와 함께 떡국 나눔 봉사활동과 더불어 군부대 이전 홍보에 구슬땀을 흘렸다. 군위군새마을회 제공. 대구 군위군 새마을회는 지난 23일 대구스타디움에서 개최된 대구마라톤대회에 참가해 먹거리부스를 운영하면서 지역 현안인 대구 군부대 이전 유치에 대해 홍보전을 펼쳤다. <br/> <br/> 대구스타디움 .."
    },
    {
        "TITLE": "[속보] 삼성전자 노사, 임단협 잠정 합의…평균 임금인상률 5.1%",
        "CATEGORY_NAMES": "사회>노동_복지",
        "URL": "https://www.bigkinds.or.kr/v2/news/newsDetailView.do?newsId=01500601.20250224142134001",
        "DATE": "20250224",
        "PROVIDER": "매일신문",
        "CONTENT": "삼성전자와 전국삼성전자노동조합(전삼노)이 2025년 임금·단체협약의 잠정합의안을 도출했다고 24일 밝혔다. 노사가 올해 임금교섭을 시작한 지난 1월 7일 이후 약 48일 만이며 지난해부터 이어온 단체교섭도 이번 임금교섭과 병행해 마무리됐다. <br/> <br/> 삼성전자는 평균 임금인상률 5.1%, 자사 제품 구매에 사용할 수 있는 패밀리넷몰 200만 포인트와 자사주.."
    },
    {
        "TITLE": "\"할인받고 국내 여행 떠나요\" 봄맞이 숙박세일 페스타",
        "CATEGORY_NAMES": "문화>요리_여행<font color=Gray> | </font>경제>자동차<font color=Gray> | </font>경제>부동산",
        "URL": "https://www.bigkinds.or.kr/v2/news/newsDetailView.do?newsId=02100601.20250224142134001",
        "DATE": "20250224",
        "PROVIDER": "한국경제",
        "CONTENT": "문화체육관광부와 한국관광공사는 '3월 여행 가는 달'을 맞아 올해 첫 '대한민국 숙박세일 페스타'를 추진한다. <br/> <br/>2025년 숙박 할인권은 국민의 해외여행 수요를 국내로 전환하고 여행 시기를 분산하기 위해 봄(3월), 여름(6월), 가을(10월) 3차례에 걸쳐 총 100만 장이 배포될 예정이다. <br/> <br/>봄 숙박 할인권은 오는 28일부터 30만 장을 배포.."
    },
    {
        "TITLE": "장기침체 빠진 양양국제공항, 올해 재도약 준비 ‘주목’",
        "CATEGORY_NAMES": "경제>산업_기업<font color=Gray> | </font>경제>취업_창업",
        "URL": "https://www.bigkinds.or.kr/v2/news/newsDetailView.do?newsId=05300152.20250224142133001",
        "DATE": "20250224",
        "PROVIDER": "설악신문",
        "CONTENT": "양양국제공항의 장기간 침체로 새로운 전환점 마련이 요구되고 있다. <br/> <br/> <br/> <br/> 옛 플라이강원의 인수합병으로 장기간 침체에 빠진 양양국제공항이 최근 대명소노그룹의 저가항공 인수전에 이어 파라타항공의 미주노선 타진 등으로 새로운 전환점을 맞을지 주목된다. <br/>국내 대표적인 리조트 운영사인 대명소노그룹이 저가항공사인 티웨이와 에어프레미아 합병을 통한 본격적인.."
    },
    {
        "TITLE": "봉화의 국립백두대간수목원, 산림복지·교육 프로그램 동시 모집",
        "CATEGORY_NAMES": "지역>강원<font color=Gray> | </font>사회>교육_시험<font color=Gray> | </font>지역>충북",
        "URL": "https://www.bigkinds.or.kr/v2/news/newsDetailView.do?newsId=01500501.20250224142133001",
        "DATE": "20250224",
        "PROVIDER": "대구일보",
        "CONTENT": "국립백두대간수목원에서 오감을 활용한 ‘나의 정원, 분경만들기’ 프로그램을 운영하고 있는 모습. 국립백두대간수목원 제공 산림청 산하 한국수목원정원관리원(이사장 심상택) 소속 국립백두대간수목원은 오는 27일부터 산림복지서비스이용권 대상자를 위한 맞춤형 산림복지 프로그램 ‘안녕! 나의 봄, 여름, 가을, 겨울’의 참가자를 모집한다. <br/> <br/> 이와 함께 3월 4.."
    },
    {
        "TITLE": "갑자기 하늘에서 자동차가 ‘뚝’…하마터면 대형사고 날뻔 (영상)",
        "CATEGORY_NAMES": "국제>아시아<font color=Gray> | </font>국제>미국_북미<font color=Gray> | </font>국제>중남미",
        "URL": "https://www.bigkinds.or.kr/v2/news/newsDetailView.do?newsId=01100401.20250224142133001",
        "DATE": "20250224",
        "PROVIDER": "동아일보",
        "CONTENT": "미국의 한 도로에서 갑자기 하늘에서 차량 등이 떨어져 대형 사고로 이어질 뻔했다. <br/> <br/>최근 X(엑스·옛 트위터) 등에는 미국 캘리포니아 주의 한 도로에서 차량들이 정상적으로 주행하던 도중 고가도로 위에서 뭔가가 아래로 추락하는 장면이 담긴 영상이 공개됐다. <br/> <br/>영상에는 놀란 운전자들이 곧장 차를 멈춰 세우고 가까스로 충돌을 피하는 장면이 담겼다. 고.."
    },
    {
        "TITLE": "성신여대, 외국인 유학생 방 구하기 돕는다...숙소 플랫폼 '맘스테이'와 업무 협약",
        "CATEGORY_NAMES": "사회>교육_시험",
        "URL": "https://www.bigkinds.or.kr/v2/news/newsDetailView.do?newsId=01101101.20250224142133001",
        "DATE": "20250224",
        "PROVIDER": "한국일보",
        "CONTENT": "성신여대 국제교육원이 주거지 선정에 어려움을 겪는 외국인 유학생들을 위해 숙소 정보 제공 플랫폼 ‘맘스테이’와 최근 업무 협약을 맺었다고 24일 밝혔다. 이 학교에서 공부하는 유학생들은 이 플랫폼에 등록된 학교 인근 숙소의 조건이나 위치 등을 영어로 제공받을 수 있어 비교적 편안하게 주거 문제를 해소할 것으로 기대된다.<br/>맘스테이는 보증금이 없거나 적고 .."
    },
    {
        "TITLE": "\"한국 안가\" 외치는 태국에서 \"한국 오세요\"…15억 매출 올렸다",
        "CATEGORY_NAMES": "국제>아시아",
        "URL": "https://www.bigkinds.or.kr/v2/news/newsDetailView.do?newsId=02100201.20250224142132001",
        "DATE": "20250224",
        "PROVIDER": "머니투데이",
        "CONTENT": "[머니투데이 오진영 기자] <br/>문화체육관광부와 한국관광공사는 태국의 해외여행 최대 성수기인 '쏭끄란 연휴'를 맞아 현지 판촉 행사를 열었다고 24일 밝혔다.<br/><br/> 태국은 동남아시아에서 가장 방한 관광객이 많은 국가이지만 최근 점차 방한 심리가 위축되고 있다. 지난해 한국을 찾은 태국인 관광객은 32만명으로 2019년 방한 태국인(57만명)의 절반 수준이다..."
    },
    {
        "TITLE": "한국산업인력공단 경기북부에 외국인근로자 한국어과정 운영",
        "CATEGORY_NAMES": "지역>대전<font color=Gray> | </font>사회>교육_시험<font color=Gray> | </font>지역>충북",
        "URL": "https://www.bigkinds.or.kr/v2/news/newsDetailView.do?newsId=01200201.20250224142131001",
        "DATE": "20250224",
        "PROVIDER": "경인일보",
        "CONTENT": "한국산업인력공단 경기북부지사에서 열린 한국어 교육과정 운영기관 업무협약식. 2025.2.24 /한국산업인력공단 경기북부지사 제공<br/> <br/><br/>외국인근로자들이 한국어를 무료로 배울 수 있는 교육과정이 경기북부지역에서 열린다. <br/> <br/><br/>24일 한국산업인력공단 경기북부지사에 따르면 경기북부에 거주하는 외국인근로자를 대상으로 한국어 교육과정이 운영될 계획이다. <br/> <br/><br/>.."
    },
    {
        "TITLE": "김영록 지사 “전남, 동계스포츠 불모지 편견 완전 깨뜨려”",
        "CATEGORY_NAMES": "스포츠>올림픽_아시안게임<font color=Gray> | </font>지역>강원<font color=Gray> | </font>스포츠>축구",
        "URL": "https://www.bigkinds.or.kr/v2/news/newsDetailView.do?newsId=01100201.20250224142131001",
        "DATE": "20250224",
        "PROVIDER": "국민일보",
        "CONTENT": "김영록(사진) 전남도지사는 24일 제106회 전국동계체육대회에 참가해 동계스포츠 불모지라는 편견을 깨뜨리며 역대 최고 득점으로 종합 7위를 달성한 전남선수단을 축하했다. <br/> <br/>전남 선수단은 이번 대회에서 금메달 19개, 은메달 6개, 동메달 10개를 획득했으며, 총373점으로 1996년 제77회 대회 참가 이래 최고 득점을 달성했다. <br/> <br/>다관왕도 다수.."
    },
    {
        "TITLE": "[이구순의 느린걸음] '휴대폰 보조금 대란'이 공정한 경쟁이었을까?",
        "CATEGORY_NAMES": "IT_과학>모바일",
        "URL": "https://www.bigkinds.or.kr/v2/news/newsDetailView.do?newsId=02100501.20250224142131001",
        "DATE": "20250224",
        "PROVIDER": "파이낸셜뉴스",
        "CONTENT": "[파이낸셜뉴스] \"지난 주말 번호이동 숫자 빨리 집계해 보내주세요\" 월요일 아침 다른 기자들보다 30분 먼저 출근해 SK텔레콤, KT, LG유플러스에 전화를 돌려둔다. 번호이동을 통해 이동통신 회사를 바꾼 가입자의 수를 크로스체크하면 지난 주말 어떤 이동통신 회사가 보조금을 '질렀는지' 확인할 수 있다. 평소 알던 대리점 서너곳을 통해 주말에 소위 공짜.."
    },
    {
        "TITLE": "정비사업 수주 ‘올인’ 삼성물산…올 수주 벌써 2조 넘겨",
        "CATEGORY_NAMES": "경제>산업_기업<font color=Gray> | </font>경제>반도체<font color=Gray> | </font>경제>부동산",
        "URL": "https://www.bigkinds.or.kr/v2/news/newsDetailView.do?newsId=02100311.20250224142131001",
        "DATE": "20250224",
        "PROVIDER": "서울경제",
        "CONTENT": "삼성물산이 올해 들어 도시정비사업에서만 2조 원이 넘는 수주액을 확보한 것으로 나타났다. 경기 불확실성에 반도체 설비 투자 등이 위축될 것으로 예상되자 주택 사업을 공격 확대하고 나선 것으로 풀이된다. <br/> <br/><br/> 24일 정비업계에 따르면 삼성물산은 올해 들어 이날까지 도시정비사업에서 총 2조 267억 원의 수주고를 기록했다. 이는 2023년(2조 951억.."
    },
    {
        "TITLE": "여당 \"민주당 김병주 최고위원, '윤석열 참수' 모형 칼 들고 사진..엽기적\"",
        "CATEGORY_NAMES": "정치>국회_정당<font color=Gray> | </font>정치>행정_자치<font color=Gray> | </font>정치>선거",
        "URL": "https://www.bigkinds.or.kr/v2/news/newsDetailView.do?newsId=04100608.20250224142124001",
        "DATE": "20250224",
        "PROVIDER": "브레이크뉴스",
        "CONTENT": "▲ 김병주 더불어민주당 의원이 11일 오후 서울 여의도 국회에서 열린 제419회국회(임시회) 제1차 본회의 윤석열 대통령 위헌적 비상계엄 선포 내란행위 관련 긴급현안질문에서 발언하고 있다. 2024.12.11.     ©뉴시스 <br/> <br/><br/><br/><br/><br/><br/><br/><br/><br/><br/><br/>   <br/> <br/><br/><br/> 브레이크뉴스 임국정 기자 = 여당인 국민의힘이 24일 \"극렬 탄핵 찬성 시위를 부추기려는.."
    },
    {
        "TITLE": "쎄니트, 작년 영업이익 32억…전년比 33.7%↓",
        "CATEGORY_NAMES": "경제>유통<font color=Gray> | </font>경제>증권_증시<font color=Gray> | </font>경제>금융_재테크",
        "URL": "https://www.bigkinds.or.kr/v2/news/newsDetailView.do?newsId=04101008.20250224142124001",
        "DATE": "20250224",
        "PROVIDER": "이데일리",
        "CONTENT": "[이데일리 원다연 기자] 쎄니트(037760)는 지난해 영업이익이 32억 6097만 1781원으로 전년 대비 33.7% 감소했다고 24일 공시했다. <br/><br/>매출액은 1324억 3987만 9532원으로 전년 대비 5.6% 감소했다. <br/><br/>회사는 “신설된 종속회사 신규사업을 위한 비용증가로 영업이익 감소 및 현금유출 없는 일회성 평가손실 및 손상인식 발생 등으로.."
    },
    {
        "TITLE": "유성구의회, \"구민 세금 한 푼도 허투루 안 쓴다\"…결산검사 착수",
        "CATEGORY_NAMES": "지역>경기<font color=Gray> | </font>정치>행정_자치<font color=Gray> | </font>지역>전북",
        "URL": "https://www.bigkinds.or.kr/v2/news/newsDetailView.do?newsId=01400601.20250224142107001",
        "DATE": "20250224",
        "PROVIDER": "충청일보",
        "CONTENT": "7명 전문위원단 위촉…재정 운용 투명성·효율성 확보3월 25일부터 20일간 예산 집행 전반 점검적법성·목적성·효율성 면밀히 검토… 철저한 점검 유성구의 재정이 올바르게 사용됐는지를 면밀히 살피기 위한 결산검사가 본격화됐다. <br/><br/>대전시 유성구의회는 24일 2024 회계연도 결산검사위원을 공식 위촉하며, 구민의 세금이 낭비 없이 적재적소에 쓰였는지를 철저히.."
    },
    {
        "TITLE": "‘부산 반얀트리 화재’ 소방시설 자체점검하다 화마 키웠을 가능성 제기",
        "CATEGORY_NAMES": "지역>부산<font color=Gray> | </font>지역>경남<font color=Gray> | </font>지역>대전",
        "URL": "https://www.bigkinds.or.kr/v2/news/newsDetailView.do?newsId=01100101.20250224142107001",
        "DATE": "20250224",
        "PROVIDER": "경향신문",
        "CONTENT": "경찰, “자체점검과 화재 연관성 조사 중”<br/><br/>사망자, 엘리베이터로 이동하다 1층서 질식<br/><br/><br/><br/>부산 반얀트리 리조트 화재는 소방시설 자체점검일에 일어난 것으로 확인됐다. 경찰은 자체점검을 위해 소방설비의 작동을 중단시켰을 가능성을 조사 중이다.<br/><br/>부산경찰청은 “불이 난 14일은 시공사의 소방시설 자체점검 기간(11~18일)의 나흘째 되는 날이었다”라며 “.."
    },
    {
        "TITLE": "꽃망울 터뜨리며 향기가득 내뿜는구나 아름답다. 사랑스럽다. 멋지다.",
        "CATEGORY_NAMES": "지역>경남<font color=Gray> | </font>지역>전남<font color=Gray> | </font>지역>광주",
        "URL": "https://www.bigkinds.or.kr/v2/news/newsDetailView.do?newsId=01100701.20250224142107001",
        "DATE": "20250224",
        "PROVIDER": "세계일보",
        "CONTENT": "한국공항공사의 희망글판이 봄을 맞아 희망이 가득 담긴 문구로 새 단장했다. <br/> <br/> 한국공항공사는 본사 외벽에 올해 첫 번째 희망글판을 설치해 봄맞이 새 단장을 했다고 24일 밝혔다. <br/> 24일 여행객들이 KAC 희망글판을 바라보고 있다. 희망글판은 공사 임직원을 대상으로 ‘봄, 새로운 시작, 도전’등을 주제로 창작문안을 공모해 선정했으며 따뜻한 격려와 .."
    },
    {
        "TITLE": "농식품부, 올해 농촌 왕진버스 사업 시작…15만명 진료 지원",
        "CATEGORY_NAMES": "지역>충북<font color=Gray> | </font>지역>경기<font color=Gray> | </font>지역>울산",
        "URL": "https://www.bigkinds.or.kr/v2/news/newsDetailView.do?newsId=01100501.20250224142105001",
        "DATE": "20250224",
        "PROVIDER": "문화일보",
        "CONTENT": "농림축산식품부는 오는 25일 경북 안동시에서 올해 농촌 왕진버스 사업을 시작한다고 24일 밝혔다.<br/><br/><br/><br/>농촌 왕진버스는 의료진이 의료 인프라가 상대적으로 취약한 농촌 지역을 찾아 지역 주민에게 의료 서비스를 제공하는 사업으로, 지난해 도입됐다. 지난 한 해 이 사업을 통해 농촌 주민 9만여 명이 양·한방 진료와 치과 검진, 구강 검사 등을 받았다. 농식.."
    }
]